{
  "meta": {
    "title": "11 Days Buddhist Pilgrimage from Malaysia | Dhesu Travel & Tours",
    "description": "11-day Buddhist pilgrimage with Bodhgaya, Sarnath, Kushinagar, Lumbini, Nalanda and Varanasi, private vehicle and guide. From RM4688 per person.",
    "keywords": "11 Days Buddhist Pilgrimage from Malaysia, India tour package, North India tour package Malaysia, Dhesu travel",
    "slug": "north-india/11-day-buddhist-pilgrimage",
    "canonicalUrl": "/tours/india/north-india/11-day-buddhist-pilgrimage",
    "ogImage": "/images/gallery/11460.jpg",
    "pkgid": "320"
  },
  "hero": {
    "badge": "North India",
    "title": "11 Days, In the Buddha's Footsteps.",
    "titleAccent": "Bodhgaya, Sarnath, Kushinagar and the Sacred Sites.",
    "intro": "Walk in the footsteps of the Buddha. The great pilgrimage sites where he was enlightened, gave his first sermon and attained final nirvana, across the plains of Bihar and Uttar Pradesh, with Lumbini just over the border. Eleven days on the Buddhist trail.",
    "breadcrumb": [
      {
        "label": "Home",
        "href": "/"
      },
      {
        "label": "India",
        "href": "/tours/india"
      },
      {
        "label": "All India Packages",
        "href": "/tours/india/all-packages"
      },
      {
        "label": "11 Days Buddhist Pilgrimage",
        "href": null
      }
    ],
    "heroImage": "/images/gallery/11460.jpg",
    "heroImageAlt": "Buddhist pilgrimage Bodhgaya Mahabodhi temple India"
  },
  "quickFacts": {
    "duration": "11 Days / 10 Nights",
    "startingPrice": "From RM4,688",
    "priceNote": "per person (twin sharing)",
    "originalPrice": "RM5,626",
    "saving": "Save RM1,875 per couple",
    "groupSize": "Private & flexible",
    "includes": [
      "Hotel Stay (10 nights)",
      "Daily Breakfast",
      "Private Vehicle & Professional Guide",
      "Return Airport Transfers",
      "Temple & Site Visits"
    ],
    "excludes": [
      "International Flights",
      "India Visa Fee (30-day e-Visa applies)",
      "ETIQA Travel Insurance (11-15 Days) RM85",
      "Entrance Fees (unless stated)",
      "Lunches and dinners (unless stated)",
      "Personal Expenses",
      "Optional tour tips"
    ]
  },
  "inclusions": {
    "icons": [
      {
        "icon": "hotel",
        "label": "Hotel"
      },
      {
        "icon": "breakfast",
        "label": "Daily Breakfast"
      },
      {
        "icon": "car",
        "label": "Private Driver Guide"
      },
      {
        "icon": "transfer",
        "label": "Airport Transfers"
      },
      {
        "icon": "private",
        "label": "100% Private Tour"
      }
    ]
  },
  "overview": {
    "sectionLabel": "About This Package",
    "heading": "11 Days Buddhist Pilgrimage: The Full Picture",
    "body": [
      "This 11 day pilgrimage follows the great sites of the Buddha's life across northern India and the Nepal border. From Bodhgaya, where he attained enlightenment beneath the Bodhi tree, to Sarnath, where he gave his first sermon, and Kushinagar, where he attained final nirvana, it traces the spiritual heart of Buddhism.",
      "Arranged privately from Malaysia, the trip is designed for Buddhist pilgrims and those drawn to the Buddha's teachings. A professional guide and a private vehicle link the sacred sites, including Rajgir and Nalanda, the great ancient university, with Lumbini, the Buddha's birthplace, just across the border in Nepal. It is a profound and well-paced journey."
    ]
  },
  "highlights": {
    "sectionLabel": "What Makes This Trip",
    "heading": "Why Travellers from Malaysia Love This Trip",
    "items": [
      {
        "title": "Bodhgaya & the Mahabodhi Temple",
        "body": "The holiest site in Buddhism, where the Buddha attained enlightenment beneath the Bodhi tree. The Mahabodhi Temple complex is a UNESCO World Heritage Site and a place of deep devotion.",
        "image": "/images/gallery/11454.jpg",
        "imageAlt": "Mahabodhi Temple Bodhgaya"
      },
      {
        "title": "Sarnath & Kushinagar",
        "body": "Sarnath, where the Buddha gave his first sermon, and Kushinagar, where he attained final nirvana, two of the four most sacred sites in Buddhism.",
        "image": "/images/gallery/11455.jpg",
        "imageAlt": "Sarnath and Kushinagar Buddhist sites"
      },
      {
        "title": "Nalanda, Rajgir & Lumbini",
        "body": "The ruins of the great Nalanda university, the hills of Rajgir, and Lumbini, the Buddha's birthplace just over the Nepal border, complete the pilgrimage.",
        "image": "/images/gallery/11456.jpg",
        "imageAlt": "Nalanda ruins Buddhist pilgrimage"
      }
    ]
  },
  "itinerary": {
    "sectionLabel": "Day by Day",
    "heading": "Your 11 Days Itinerary",
    "days": [
      {
        "day": 1,
        "title": "Arrive Gaya / Bodhgaya",
        "meals": "No meals",
        "description": "Met at Gaya airport and transferred to Bodhgaya, the holiest Buddhist site.",
        "suggestedActivities": [
          "Settle in Bodhgaya",
          "Evening at the Mahabodhi Temple",
          "Meditation under the Bodhi tree"
        ]
      },
      {
        "day": 2,
        "title": "Bodhgaya Sightseeing",
        "meals": "Breakfast",
        "description": "A full day at the sacred sites of Bodhgaya.",
        "suggestedActivities": [
          "Mahabodhi Temple and Bodhi tree",
          "Great Buddha statue",
          "International monasteries",
          "Sujata village"
        ]
      },
      {
        "day": 3,
        "title": "Bodhgaya to Rajgir & Nalanda",
        "meals": "Breakfast",
        "description": "The hills of Rajgir and the ruins of Nalanda university.",
        "suggestedActivities": [
          "Griddhakuta (Vulture's Peak)",
          "Rajgir hot springs",
          "Nalanda university ruins",
          "Drive onward"
        ]
      },
      {
        "day": 4,
        "title": "To Patna / Vaishali",
        "meals": "Breakfast",
        "description": "Travel via Vaishali, an important Buddhist site.",
        "suggestedActivities": [
          "Vaishali Ashokan pillar",
          "Relic Stupa",
          "Drive to Patna area"
        ]
      },
      {
        "day": 5,
        "title": "To Kushinagar",
        "meals": "Breakfast",
        "description": "Drive to Kushinagar, where the Buddha attained final nirvana.",
        "suggestedActivities": [
          "Drive to Kushinagar",
          "Mahaparinirvana Temple",
          "Reclining Buddha",
          "Ramabhar Stupa"
        ]
      },
      {
        "day": 6,
        "title": "Kushinagar to Lumbini (Nepal)",
        "meals": "Breakfast",
        "description": "Cross into Nepal to Lumbini, the Buddha's birthplace.",
        "suggestedActivities": [
          "Border crossing",
          "Maya Devi Temple",
          "Ashokan pillar",
          "Sacred garden and monasteries"
        ]
      },
      {
        "day": 7,
        "title": "Lumbini to Sravasti",
        "meals": "Breakfast",
        "description": "Return to India and drive to Sravasti.",
        "suggestedActivities": [
          "Drive to Sravasti",
          "Jetavana Monastery",
          "Anandabodhi tree",
          "Ancient stupas"
        ]
      },
      {
        "day": 8,
        "title": "Sravasti to Lucknow",
        "meals": "Breakfast",
        "description": "Travel towards Lucknow with cultural stops.",
        "suggestedActivities": [
          "Drive to Lucknow",
          "Bara Imambara (optional)",
          "Evening at leisure"
        ]
      },
      {
        "day": 9,
        "title": "Lucknow to Varanasi",
        "meals": "Breakfast",
        "description": "Travel to Varanasi and Sarnath.",
        "suggestedActivities": [
          "Travel to Varanasi",
          "Sarnath Dhamek Stupa",
          "Sarnath Museum",
          "Evening Ganga Aarti"
        ]
      },
      {
        "day": 10,
        "title": "Varanasi",
        "meals": "Breakfast",
        "description": "Sunrise boat and the sacred city.",
        "suggestedActivities": [
          "Sunrise boat ride",
          "Kashi Vishwanath Temple",
          "Old city lanes",
          "Silk weavers"
        ]
      },
      {
        "day": 11,
        "title": "Depart Varanasi",
        "meals": "Breakfast",
        "description": "Transfer to the airport for your onward flight.",
        "suggestedActivities": [
          "Final ghat visit",
          "Airport transfer"
        ]
      }
    ]
  },
  "hotelOptions": {
    "sectionLabel": "Hotel Options",
    "heading": "Choose Your Comfort Level",
    "subheading": "Centrally located hotels with easy access to the main sights. Pick the tier that suits your style.",
    "tiers": [
      {
        "tier": "3 Star",
        "label": "Budget Friendly",
        "hotel": "3-star hotels or similar",
        "pricing": [
          {
            "label": "Min 2 Adults (Toyota Etios)",
            "price": "RM4688 per person"
          },
          {
            "label": "Min 4 Adults (Toyota Innova)",
            "price": "RM4638 per person"
          },
          {
            "label": "Min 8 Adults (Tempo Traveller)",
            "price": "RM4588 per person"
          }
        ],
        "fromPrice": "RM4688"
      },
      {
        "tier": "4 Star",
        "label": "Value Plus Comfort",
        "hotel": "4-star hotels or similar",
        "pricing": [
          {
            "label": "Min 2 Adults (Toyota Etios)",
            "price": "RM5188 per person"
          },
          {
            "label": "Min 4 Adults (Toyota Innova)",
            "price": "RM5148 per person"
          },
          {
            "label": "Min 8 Adults (Tempo Traveller)",
            "price": "RM5108 per person"
          }
        ],
        "fromPrice": "RM5188",
        "popular": true
      },
      {
        "tier": "5 Star",
        "label": "Premium Value Stay",
        "hotel": "5-star hotels or similar",
        "pricing": [
          {
            "label": "Min 2 Adults (Toyota Etios)",
            "price": "RM5988 per person"
          },
          {
            "label": "Min 4 Adults (Toyota Innova)",
            "price": "RM5958 per person"
          },
          {
            "label": "Min 8 Adults (Tempo Traveller)",
            "price": "RM5928 per person"
          }
        ],
        "fromPrice": "RM5988"
      }
    ]
  },
  "whyBook": {
    "sectionLabel": "Why Dhesu",
    "heading": "The Buddhist Trail, Routed With Reverence",
    "body": "The Buddhist sites are spread across Bihar, Uttar Pradesh and the Nepal border, with a crossing to manage. We handle the routing, the border and a guide versed in the Buddha's life. Dhesu has arranged pilgrimages since 1988.",
    "points": [
      {
        "icon": "shield",
        "title": "MATTA & IATA Registered",
        "body": "Fully licensed Malaysian travel agency. We guide you through India e-Visa documentation with every booking."
      },
      {
        "icon": "clock",
        "title": "Private Tours, Daily Departures",
        "body": "No minimum group to wait for. Your trip runs on your dates, your pace, your own vehicle and guide."
      },
      {
        "icon": "phone",
        "title": "A Real Team to Call",
        "body": "Reachable throughout your trip. Flight delayed, your guide waits. Plans change, we adapt on the ground."
      },
      {
        "icon": "tag",
        "title": "Group & Custom Pricing",
        "body": "Travelling as a family or group lowers the per-person cost. Ask us for a tailored quote."
      }
    ]
  },
  "seoContent": {
    "sections": [
      {
        "heading": "Buddhist Pilgrimage Tour from Malaysia",
        "body": "This 11 day pilgrimage follows the great sites of the Buddha's life across northern India and into Nepal. From Bodhgaya's enlightenment site to Sarnath, Kushinagar and Lumbini, it traces the spiritual heart of Buddhism.\n\nWith a professional guide and a private vehicle, the trip handles the considerable distances and the Nepal border crossing, with the ancient university of Nalanda and Rajgir along the way.\n\nIt is a profound journey for Buddhist pilgrims and anyone drawn to the Buddha's teachings."
      },
      {
        "heading": "The Four Great Sites and Beyond",
        "body": "Buddhism recognises four principal pilgrimage sites: Lumbini, where the Buddha was born; Bodhgaya, where he attained enlightenment; Sarnath, where he gave his first sermon; and Kushinagar, where he attained final nirvana. This pilgrimage covers all four.\n\nIt also includes Nalanda, the great ancient seat of Buddhist learning, Rajgir, Vaishali and Sravasti, giving a fuller picture of the Buddha's life and the spread of his teachings."
      }
    ]
  },
  "faq": {
    "sectionLabel": "Common Questions",
    "heading": "Questions About This Package",
    "items": [
      {
        "question": "Do Malaysians need a visa for India?",
        "answer": "Yes. Malaysian passport holders apply for an India e-Visa online before departure. The tourist e-Visa covers tourism and short visits and is valid for 30 days from entry. The application is on the official India e-Visa portal, and Dhesu walks you through it when you book. Visa fees are not included in the package price."
      },
      {
        "question": "Which airport does this trip use?",
        "answer": "This is a land-only package: hotels, transfers, tours and guide are included, but international flights are not. Most Malaysian travellers fly from Kuala Lumpur International Airport (KLIA) to Gaya and Varanasi Airports (GAY / VNS). We can recommend suitable flights and timings on request."
      },
      {
        "question": "Do I need a separate visa for the Nepal section?",
        "answer": "This pilgrimage crosses into Nepal to visit Lumbini. Visa requirements for Nepal differ from India, and Nepal offers visa on arrival for many nationalities. We will advise on the specific requirements for your passport before travel."
      },
      {
        "question": "What is the best time for this pilgrimage?",
        "answer": "October to March offers the most comfortable weather across the plains. The cooler winter months are ideal for the many site visits. Summers are extremely hot, and the monsoon brings heavy rain that can affect travel."
      },
      {
        "question": "Is this trip suitable for non-Buddhists?",
        "answer": "Yes. While it is a meaningful pilgrimage for Buddhists, the sites are also of great historical and cultural significance. Anyone interested in the life of the Buddha, ancient history or Indian heritage will find it rewarding."
      }
    ]
  },
  "relatedPackages": [
    {
      "id": "india-11d-sacred-trails",
      "name": "11 Days Sacred Trails of India",
      "price": "From RM3,888",
      "duration": "11D10N",
      "slug": "north-india/11-day-sacred-trails",
      "image": "/images/gallery/15212.jpg"
    },
    {
      "id": "india-3d-varanasi-sunrise-sunset",
      "name": "3 Days Varanasi: Sunrise, Sunset & Ganga Aarti",
      "price": "From RM698",
      "duration": "3D2N",
      "slug": "north-india/3-day-varanasi-ganga-aarti",
      "image": "/images/gallery/13568.jpg"
    },
    {
      "id": "india-7d-sikkim",
      "name": "7 Days Sikkim & the Eastern Himalayas",
      "price": "From RM4,088",
      "duration": "7D6N",
      "slug": "north-india/7-day-sikkim",
      "image": "/images/gallery/12223.jpg"
    }
  ],
  "cta": {
    "heading": "Ready for the Buddhist pilgrimage?",
    "subheading": "Tell us your dates and group size for a confirmed quote.",
    "phone": "+6019 336 4465",
    "whatsapp": "60193364465",
    "email": "tours@dhesu.travel",
    "address": "Level 2 and 3, Wisma Dhesu, No. 5 Jalan Bangsar Utama 3, 59000 Kuala Lumpur.",
    "bgImage": "/images/gallery/11453.jpg"
  },
  "schema": {
    "type": "TouristTrip",
    "name": "11 Days Buddhist Pilgrimage Tour from Malaysia",
    "description": "11-day Buddhist pilgrimage with Bodhgaya, Sarnath, Kushinagar, Lumbini, Nalanda and Varanasi, private vehicle and guide. From RM4688 per person.",
    "provider": "Dhesu Travel & Tours",
    "url": "https://dhesu.travel/tours/india/north-india/11-day-buddhist-pilgrimage",
    "startLocation": "Gaya Airport",
    "endLocation": "Lal Bahadur Shastri International Airport",
    "duration": "P11D",
    "offers": {
      "price": "4688",
      "priceCurrency": "MYR",
      "availability": "https://schema.org/InStock"
    }
  }
}
